cellregistry/__init__.py
cellregistry/models.py
cellregistry/migrations/__init__.py
cellregistry-0.1.0.dist-info/WHEEL
cellregistry-0.1.0.dist-info/METADATA
cellregistry-0.1.0.dist-info/RECORD
