Metadata-Version: 2.1
Name: cellregistry
Version: 0.1.0
Summary: A reference manager.
Author-email: Lamin Labs <open-source@lamin.ai>
Requires-Dist: lamindb
Requires-Dist: pre-commit ; extra == "dev"
Requires-Dist: nox ; extra == "dev"
Requires-Dist: pytest>=6.0 ; extra == "dev"
Requires-Dist: pytest-cov ; extra == "dev"
Requires-Dist: nbproject_test ; extra == "dev"
Project-URL: Home, https://github.com/laminlabs/cellregistry
Provides-Extra: dev
